{
    "-MTpclfzY9GLtKDsDYTs": {
        "firebaseKey": "-MTpclfzY9GLtKDsDYTs",
        "language_id": 12345,
        "name": "javascript",
        "description": "A programming language with functions.",
        "category": "language"
    },
    "-MTpcli9kmjpvbdr-ckb": {
        "firebaseKey": "-MTpcli9kmjpvbdr-ckb",
        "language_id": 12345,
        "name": "javascript",
        "description": "A programming language with functions.",
        "category": "language"
    },
    "-MTpcliA_-GtWZHpb8sf": {
        "firebaseKey": "-MTpcliA_-GtWZHpb8sf",
        "language_id": 12345,
        "name": "javascript",
        "description": "A programming language with functions.",
        "category": "language"
    },
    "-MTpcliCeUeUNMpZ-Kog": {
        "firebaseKey": "-MTpcliCeUeUNMpZ-Kog",
        "language_id": 12345,
        "name": "javascript",
        "description": "A programming language with functions.",
        "category": "language"
    }
}